streamlit_sidemenu/__init__.py
streamlit_sidemenu/frontend/dist/index.html
streamlit_sidemenu/frontend/dist/assets/index.34a5a3a0.js
streamlit_sidemenu/frontend/dist/assets/index.39969be4.js
streamlit_sidemenu/frontend/dist/assets/vendor.90a306ac.js
streamlit_sidemenu-0.0.4.dist-info/LICENSE
streamlit_sidemenu-0.0.4.dist-info/METADATA
streamlit_sidemenu-0.0.4.dist-info/WHEEL
streamlit_sidemenu-0.0.4.dist-info/top_level.txt
streamlit_sidemenu-0.0.4.dist-info/RECORD
