Metadata-Version: 2.1
Name: streamlit-sidemenu
Version: 0.0.4
Summary: Sidebar Menu custom component for Streamlit
Home-page: https://github.com/ais-one/favv
Author: Aaron Gong
Author-email: aaronjxz@gmail.com
License: Apache Software License
Project-URL: Bug Tracker, https://github.com/ais-one/favv/issues
Keywords: streamlit,sidebar,menu
Platform: UNKNOWN
Classifier: Development Status :: 2 - Pre-Alpha
Classifier: Intended Audience :: Developers
Classifier: License :: OSI Approved :: Apache Software License
Classifier: Programming Language :: Python :: 3
Requires-Python: >=3.6
Requires-Dist: streamlit (>=0.63)
